linear_combination/__init__.py
linear_combination/linear_combination.py
linear_combination/words.py
linear_combination_py-0.1.4.dist-info/METADATA
linear_combination_py-0.1.4.dist-info/RECORD
linear_combination_py-0.1.4.dist-info/WHEEL
linear_combination_py-0.1.4.dist-info/top_level.txt
