Metadata-Version: 2.1
Name: linear-combination-py
Version: 0.1.4
Summary: A small library implementing linear combinations of "stuff".
Home-page: https://github.com/diehlj/linear-combination-py
Author: Joscha Diehl
Author-email: UNKNOWN
License: Eclipse Public License
Platform: UNKNOWN
Requires-Dist: numpy
Requires-Dist: scipy
Requires-Dist: sympy
